muttlib/__init__.py
muttlib/dbconn/__init__.py
muttlib/dbconn/base.py
muttlib/dbconn/bigquery.py
muttlib/dbconn/hive.py
muttlib/dbconn/ibis.py
muttlib/dbconn/mongo.py
muttlib/dbconn/mysql.py
muttlib/dbconn/oracle.py
muttlib/dbconn/postgres.py
muttlib/dbconn/redshift.py
muttlib/dbconn/snowflake.py
muttlib/dbconn/sqlite.py
muttlib/dbconn/sqlserver.py
muttlib/dbconn/teradata.py
muttlib/dbconn/trino.py
muttlib/file_processing.py
muttlib/forecast.py
muttlib/gdrive.py
muttlib/gsheetsconn.py
muttlib/plotting/__init__.py
muttlib/plotting/constants.py
muttlib/plotting/plot.py
muttlib/utils.py
muttlib-1.4.27.dist-info/LICENSE
muttlib-1.4.27.dist-info/METADATA
muttlib-1.4.27.dist-info/WHEEL
muttlib-1.4.27.dist-info/RECORD
