Metadata-Version: 2.1
Name: muttlib
Version: 1.4.27
Summary: Collection of helper modules by Mutt Data.
Home-page: https://github.com/MuttData/muttlib
License: Apache-2.0
Keywords: data,muttdata
Author: Mutt Data
Author-email: info@muttdata.ai
Requires-Python: >=3.8,<3.11
Classifier: License :: OSI Approved :: Apache Software License
Classifier: Operating System :: OS Independent
Classifier: Programming Language :: Python :: 3
Classifier: Programming Language :: Python :: 3.8
Classifier: Programming Language :: Python :: 3.9
Classifier: Programming Language :: Python :: 3.10
Provides-Extra: all
Provides-Extra: bigquery
Provides-Extra: forecast
Provides-Extra: gdrive
Provides-Extra: gsheets
Provides-Extra: hive
Provides-Extra: ibis
Provides-Extra: mongo
Provides-Extra: mysql
Provides-Extra: oracle
Provides-Extra: postgres
Provides-Extra: pyarrow
Provides-Extra: redshift
Provides-Extra: snowflake
Provides-Extra: sqlserver
Provides-Extra: teradata
Provides-Extra: test
Provides-Extra: trino
Requires-Dist: Deprecated (>=1.2.13,<2.0.0)
Requires-Dist: Jinja2 (>=2.11.3,<3.1.0)
Requires-Dist: MarkupSafe (>=0.2.3,<2.1.0)
Requires-Dist: Pillow (>=9.1.1)
Requires-Dist: PyHive (>=0.6.1) ; extra == "hive" or extra == "all"
Requires-Dist: PyJWT (>=2.4.0)
Requires-Dist: PyMySQL (>=1.0.2,<2.0.0) ; extra == "mysql" or extra == "all"
Requires-Dist: PyYAML (>=5.1,<7.0)
Requires-Dist: SQLAlchemy (>=1.3,<2.0)
Requires-Dist: bandit (>=1.7.2,<2.0.0) ; extra == "test" or extra == "all"
Requires-Dist: betamax (>=0.8.1,<0.9.0) ; extra == "test" or extra == "all"
Requires-Dist: betamax-serializers (>=0.2.1,<0.3.0) ; extra == "test" or extra == "all"
Requires-Dist: cryptography (==3.4.7) ; extra == "snowflake" or extra == "all"
Requires-Dist: cx-Oracle (>=8.3.0,<9.0.0) ; extra == "oracle" or extra == "all"
Requires-Dist: freezegun (>=1.1.0,<2.0.0) ; extra == "test" or extra == "all"
Requires-Dist: google-cloud-bigquery (>=2.34.4,<2.35.0) ; extra == "bigquery" or extra == "all"
Requires-Dist: gspread-pandas (>=2.3.0,<3.0.0) ; extra == "gsheets" or extra == "all"
Requires-Dist: holidays (>=0.10.2) ; extra == "test" or extra == "forecast" or extra == "all" or extra == "all"
Requires-Dist: ibis-framework[impala] (==3.2.0) ; extra == "ibis" or extra == "all"
Requires-Dist: interrogate (>=1.5.0,<2.0.0) ; extra == "test" or extra == "all"
Requires-Dist: ipython (>=8.0.1)
Requires-Dist: jinjasql (>=0.1.8,<0.2.0)
Requires-Dist: lxml (>=4.9.1)
Requires-Dist: matplotlib (>=3.5.0,<4.0.0)
Requires-Dist: nox (>=2021.10.1,<2022.0.0) ; extra == "test" or extra == "all"
Requires-Dist: numpy (>=1.22.0,<2.0)
Requires-Dist: oauth2client (>=4.1.3,<5.0.0) ; extra == "gdrive" or extra == "all"
Requires-Dist: pandas (>=1.0.0)
Requires-Dist: progressbar2 (>=3.55.0,<4.0.0)
Requires-Dist: prophet (>=1.0.1,<2.0.0) ; extra == "forecast" or extra == "all"
Requires-Dist: psycopg2-binary (>=2.9.2,<3.0.0) ; extra == "postgres" or extra == "redshift" or extra == "all" or extra == "all"
Requires-Dist: pyarrow (==6.0.0) ; extra == "pyarrow" or extra == "ibis" or extra == "test" or extra == "all" or extra == "all" or extra == "all"
Requires-Dist: pymongo (>=3.12.1,<4.0.0) ; extra == "mongo" or extra == "all"
Requires-Dist: pymssql (>=2.2.2,<3.0.0) ; extra == "sqlserver" or extra == "all"
Requires-Dist: pyparsing (<3) ; extra == "redshift" or extra == "all"
Requires-Dist: pytest (>=6.2.5,<7.0.0) ; extra == "test" or extra == "all"
Requires-Dist: pytest-cov (>=3.0.0,<4.0.0) ; extra == "test" or extra == "all"
Requires-Dist: pytest-html (>=3.1.1,<4.0.0) ; extra == "test" or extra == "all"
Requires-Dist: pytest-mpl (>=0.12.1,<0.13.0) ; extra == "test" or extra == "all"
Requires-Dist: pytest-xdist (>=2.4.0,<3.0.0) ; extra == "test" or extra == "all"
Requires-Dist: requests (>=2.26.0,<3.0.0) ; extra == "gdrive" or extra == "all"
Requires-Dist: scikit-learn (>=1.0.1,<2.0.0)
Requires-Dist: scipy (>=1.7.2,<2.0.0)
Requires-Dist: snowflake-connector-python (>=2.7.1,<3.0.0) ; extra == "snowflake" or extra == "all"
Requires-Dist: snowflake-sqlalchemy (>=1.2.4,<=1.4.4,!=1.2.5) ; extra == "snowflake" or extra == "all"
Requires-Dist: sqlalchemy-redshift (==0.8.6) ; extra == "redshift" or extra == "all"
Requires-Dist: teradatasql (==17.0.0.8) ; extra == "teradata" or extra == "all"
Requires-Dist: thrift (>=0.16.0,<0.17.0) ; extra == "hive" or extra == "all"
Requires-Dist: trino[sqlalchemy] (==0.320.0)
Requires-Dist: types-PyMySQL (>=1.0.11,<2.0.0)
Requires-Dist: types-requests (>=2.27.7,<3.0.0)
Requires-Dist: ujson (>=5.4.0)
Project-URL: Repository, https://github.com/MuttData/muttlib
